mlx.json_to_mako-0.4-nspkg.pth
mlx/__version__.py
mlx/json_to_mako.py
mlx.json_to_mako-0.4.dist-info/DESCRIPTION.rst
mlx.json_to_mako-0.4.dist-info/METADATA
mlx.json_to_mako-0.4.dist-info/RECORD
mlx.json_to_mako-0.4.dist-info/WHEEL
mlx.json_to_mako-0.4.dist-info/entry_points.txt
mlx.json_to_mako-0.4.dist-info/metadata.json
mlx.json_to_mako-0.4.dist-info/namespace_packages.txt
mlx.json_to_mako-0.4.dist-info/top_level.txt
