Metadata-Version: 2.0
Name: mlx.json-to-mako
Version: 0.4
Summary: Convertor for JSON database(s) to MAKO templated output
Home-page: https://github.com/melexis/json-to-mako
Author: Stein Heselmans
Author-email: teh@melexis.com
License: Apache License, Version 2.0
Keywords: json,mako
Platform: any
Classifier: Development Status :: 2 - Pre-Alpha
Classifier: Environment :: Console
Classifier: Environment :: Web Environment
Classifier: Framework :: Sphinx :: Extension
Classifier: Intended Audience :: Developers
Classifier: License :: OSI Approved :: Apache Software License
Classifier: Operating System :: OS Independent
Classifier: Programming Language :: Python
Classifier: Programming Language :: Python :: 2.7
Classifier: Programming Language :: Python :: 3.4
Classifier: Programming Language :: Python :: 3.5
Classifier: Programming Language :: Python :: 3.6
Classifier: Topic :: Utilities
Requires-Dist: mako
